zf_rush/__init__.py
zf_rush/async_decorators.py
zf_rush/client.py
zf_rush/config.py
zf_rush/proxy.py
zf_rush-1.1.1.dist-info/licenses/LICENSE
zf_rush-1.1.1.dist-info/METADATA
zf_rush-1.1.1.dist-info/WHEEL
zf_rush-1.1.1.dist-info/top_level.txt
zf_rush-1.1.1.dist-info/RECORD
