Metadata-Version: 2.4
Name: zf_rush
Version: 1.1.1
Summary: High-level async API client and scheduler framework
Author-email: zerofire <fire2019@qq.com>
Project-URL: Homepage, https://github.com/FlameFires/zf_rush/
Project-URL: Repository, https://github.com/FlameFires/zf_rush/
Keywords: async,api,scheduler,framework,rusher,high-level
Classifier: Programming Language :: Python :: 3
Classifier: License :: OSI Approved :: MIT License
Classifier: Operating System :: OS Independent
Requires-Python: >=3.12
License-File: LICENSE
Requires-Dist: fake-useragent>=2.1.0
Requires-Dist: httpx[http2]>=0.28.1
Requires-Dist: loguru>=0.7.3
Dynamic: license-file
